<?xml version="1.0" encoding="UTF-8"?>

	<!--
	Created by ZK Studio
-->

<zk>
	<device-config>
		<device-type>ajax</device-type>
		<timeout-uri>/timeout.zul</timeout-uri>
		<!--
			An empty URL can cause the browser to reload the same URL
		-->
	</device-config>

	<!-- Threadlocal para filtros de control de usuarios -->
	<listener>
		<description>ThreadLocal Synchronization Listener</description>
		<listener-class>org.zkoss.zkplus.util.ThreadLocalListener
		</listener-class>
	</listener>

	<preference>
		<name>ThreadLocal</name>
		<value>
			ar.edu.utn.frba.proyecto.citysoft.user.UserContext=tlUserContext;
		</value>
	</preference>

</zk>
